LICENSE.txt
setup.cfg
setup.py
beeprint/__init__.py
beeprint/config.py
beeprint/constants.py
beeprint/debug_kit.py
beeprint/helper.py
beeprint/printer.py
beeprint/terminal_size.py
beeprint/utils.py
beeprint.egg-info/PKG-INFO
beeprint.egg-info/SOURCES.txt
beeprint.egg-info/dependency_links.txt
beeprint.egg-info/requires.txt
beeprint.egg-info/top_level.txt
beeprint/helpers/__init__.py
beeprint/helpers/string.py
beeprint/lib/__init__.py
beeprint/lib/position_dict.py
beeprint/lib/search_up_tree.py
beeprint/lib/test_main.py
beeprint/lib/walker.py
beeprint/models/__init__.py
beeprint/models/block.py
beeprint/models/wrapper.py