Metadata-Version: 2.1
Name: beeprint
Version: 2.4.11
Summary: make your debug printing more friendly
Home-page: https://github.com/panyanyany/beeprint
Download-URL: https://github.com/panyanyany/beeprint/archive/master.zip
Author: Yangyang Pan
Author-email: 568397440@qq.com
Keywords: print,pprint,format,debug
Classifier: Programming Language :: Python
Classifier: Programming Language :: Python :: 3
Classifier: License :: OSI Approved :: BSD License
Classifier: Operating System :: OS Independent
Classifier: Environment :: Console
Classifier: Development Status :: 4 - Beta
Classifier: Intended Audience :: Developers
Classifier: Topic :: Software Development
Classifier: Topic :: Utilities
License-File: LICENSE.txt
